odoo/addons/l10n_it_fatturapa_out_triple_discount/README.rst
odoo/addons/l10n_it_fatturapa_out_triple_discount/__init__.py
odoo/addons/l10n_it_fatturapa_out_triple_discount/__manifest__.py
odoo/addons/l10n_it_fatturapa_out_triple_discount/i18n/l10n_it_fatturapa_out_triple_discount.pot
odoo/addons/l10n_it_fatturapa_out_triple_discount/readme/CONTRIBUTORS.rst
odoo/addons/l10n_it_fatturapa_out_triple_discount/readme/DESCRIPTION.rst
odoo/addons/l10n_it_fatturapa_out_triple_discount/static/description/icon.png
odoo/addons/l10n_it_fatturapa_out_triple_discount/static/description/index.html
odoo/addons/l10n_it_fatturapa_out_triple_discount/tests/__init__.py
odoo/addons/l10n_it_fatturapa_out_triple_discount/tests/test_fatturapa_triple_discount.py
odoo/addons/l10n_it_fatturapa_out_triple_discount/tests/data/IT06363391001_00001.xml
odoo/addons/l10n_it_fatturapa_out_triple_discount/wizards/__init__.py
odoo/addons/l10n_it_fatturapa_out_triple_discount/wizards/wizard_export_fatturapa.py
odoo12_addon_l10n_it_fatturapa_out_triple_discount-12.0.2.0.1.dist-info/METADATA
odoo12_addon_l10n_it_fatturapa_out_triple_discount-12.0.2.0.1.dist-info/WHEEL
odoo12_addon_l10n_it_fatturapa_out_triple_discount-12.0.2.0.1.dist-info/top_level.txt
odoo12_addon_l10n_it_fatturapa_out_triple_discount-12.0.2.0.1.dist-info/RECORD
