Metadata-Version: 2.1
Name: odoo12-addon-l10n-it-fatturapa-out-triple-discount
Version: 12.0.2.0.1
Summary: Modulo ponte tra emissione fatture elettroniche e sconto triplo
Home-page: https://github.com/OCA/l10n-italy/tree/12.0/l10n_it_fatturapa_out_triple_discount
Author: Agile Business Group, Odoo Community Association (OCA)
Author-email: support@odoo-community.org
License: AGPL-3
Platform: UNKNOWN
Classifier: Programming Language :: Python
Classifier: Framework :: Odoo
Classifier: License :: OSI Approved :: GNU Affero General Public License v3
Classifier: Development Status :: 4 - Beta
Requires-Python: >=3.5
Requires-Dist: odoo12-addon-account-invoice-triple-discount
Requires-Dist: odoo12-addon-l10n-it-fatturapa-out
Requires-Dist: odoo (<12.1dev,>=12.0a)
